inscripta/biocantor/__init__.py
inscripta/biocantor/constants.py
inscripta/biocantor/exc.py
inscripta/biocantor/gene/__init__.py
inscripta/biocantor/gene/biotype.py
inscripta/biocantor/gene/cds.py
inscripta/biocantor/gene/cds_frame.py
inscripta/biocantor/gene/codon.py
inscripta/biocantor/gene/collections.py
inscripta/biocantor/gene/feature.py
inscripta/biocantor/gene/interval.py
inscripta/biocantor/gene/transcript.py
inscripta/biocantor/io/__init__.py
inscripta/biocantor/io/exc.py
inscripta/biocantor/io/models.py
inscripta/biocantor/io/parser.py
inscripta/biocantor/io/bed/__init__.py
inscripta/biocantor/io/bed/bed.py
inscripta/biocantor/io/bed/exc.py
inscripta/biocantor/io/fasta/__init__.py
inscripta/biocantor/io/fasta/exc.py
inscripta/biocantor/io/fasta/fasta.py
inscripta/biocantor/io/features/__init__.py
inscripta/biocantor/io/genbank/__init__.py
inscripta/biocantor/io/genbank/constants.py
inscripta/biocantor/io/genbank/exc.py
inscripta/biocantor/io/genbank/parser.py
inscripta/biocantor/io/genbank/writer.py
inscripta/biocantor/io/gff3/__init__.py
inscripta/biocantor/io/gff3/constants.py
inscripta/biocantor/io/gff3/exc.py
inscripta/biocantor/io/gff3/parser.py
inscripta/biocantor/io/gff3/rows.py
inscripta/biocantor/io/gff3/writer.py
inscripta/biocantor/io/ncbi/__init__.py
inscripta/biocantor/io/ncbi/exc.py
inscripta/biocantor/io/ncbi/tbl_writer.py
inscripta/biocantor/location/__init__.py
inscripta/biocantor/location/distance.py
inscripta/biocantor/location/location.py
inscripta/biocantor/location/location_impl.py
inscripta/biocantor/location/strand.py
inscripta/biocantor/parent/__init__.py
inscripta/biocantor/parent/parent.py
inscripta/biocantor/sequence/__init__.py
inscripta/biocantor/sequence/alphabet.py
inscripta/biocantor/sequence/sequence.py
inscripta/biocantor/util/__init__.py
inscripta/biocantor/util/bins.py
inscripta/biocantor/util/enum.py
inscripta/biocantor/util/hashing.py
inscripta/biocantor/util/object_validation.py
inscripta/biocantor/util/ordering.py
BioCantor-0.4.5.dist-info/LICENSE.txt
BioCantor-0.4.5.dist-info/METADATA
BioCantor-0.4.5.dist-info/WHEEL
BioCantor-0.4.5.dist-info/top_level.txt
BioCantor-0.4.5.dist-info/RECORD
