Metadata-Version: 2.1
Name: BioCantor
Version: 0.4.5
Summary: Flexible feature arithmetic, seamlessly integrated with nested coordinate systems.
Home-page: https://github.com/InscriptaLabs/BioCantor
Author: Inscripta, Inc.
License: UNKNOWN
Platform: UNKNOWN
Classifier: Programming Language :: Python :: 3
Classifier: License :: OSI Approved :: MIT License
Classifier: Operating System :: OS Independent
Requires-Dist: biopython
Requires-Dist: marshmallow-dataclass[enum,union]
Requires-Dist: marshmallow
Requires-Dist: methodtools
Provides-Extra: all
Requires-Dist: gffutils ; extra == 'all'
Requires-Dist: black ; extra == 'all'
Requires-Dist: flake8 ; extra == 'all'
Requires-Dist: pytest ; extra == 'all'
Requires-Dist: pytest-cov ; extra == 'all'
Requires-Dist: pytest-error-for-skips ; extra == 'all'
Requires-Dist: Sphinx ; extra == 'all'
Requires-Dist: sphinx-rtd-theme ; extra == 'all'
Requires-Dist: sphinx-autoapi ; extra == 'all'
Requires-Dist: graphviz ; extra == 'all'
Requires-Dist: nbconvert ; extra == 'all'
Requires-Dist: nbsphinx ; extra == 'all'
Requires-Dist: ipykernel ; extra == 'all'
Requires-Dist: pandoc ; extra == 'all'
Requires-Dist: recommonmark ; extra == 'all'
Requires-Dist: tornado (>=5.1) ; extra == 'all'
Provides-Extra: docs
Requires-Dist: Sphinx ; extra == 'docs'
Requires-Dist: sphinx-rtd-theme ; extra == 'docs'
Requires-Dist: sphinx-autoapi ; extra == 'docs'
Requires-Dist: graphviz ; extra == 'docs'
Requires-Dist: nbconvert ; extra == 'docs'
Requires-Dist: nbsphinx ; extra == 'docs'
Requires-Dist: ipykernel ; extra == 'docs'
Requires-Dist: pandoc ; extra == 'docs'
Requires-Dist: recommonmark ; extra == 'docs'
Provides-Extra: io
Requires-Dist: gffutils ; extra == 'io'
Provides-Extra: optional
Requires-Dist: tornado (>=5.1) ; extra == 'optional'
Provides-Extra: test
Requires-Dist: black ; extra == 'test'
Requires-Dist: flake8 ; extra == 'test'
Requires-Dist: pytest ; extra == 'test'
Requires-Dist: pytest-cov ; extra == 'test'
Requires-Dist: pytest-error-for-skips ; extra == 'test'
